helloworld.py
helloworld_nik12-0.0.4.dist-info/LICENSE.txt
helloworld_nik12-0.0.4.dist-info/METADATA
helloworld_nik12-0.0.4.dist-info/WHEEL
helloworld_nik12-0.0.4.dist-info/top_level.txt
helloworld_nik12-0.0.4.dist-info/RECORD
