Metadata-Version: 2.1
Name: helloworld-nik12
Version: 0.0.4
Summary: say hello
Home-page: https://github.com/nikhar1210
Author: Nikhar
Author-email: nikhar1210@gmail.com
License: UNKNOWN
Platform: UNKNOWN
Classifier: Programming Language :: Python :: 3
Classifier: Programming Language :: Python :: 3.6
Classifier: Programming Language :: Python :: 3.7
Classifier: License :: OSI Approved :: GNU General Public License v2 or later (GPLv2+)
Classifier: Operating System :: OS Independent
